{
    "loading": false,
    "completed": false,
    "total": "100",
    "questions": [{
        "type": "multiplechoice",
        "id": "ready",
        "tagline": "Быть стрессоустойчивым очень важно при работе с детьми. Мы предлагаем вам пройти тест на наличие этого качества. Вам необходимо прочитать утверждения и выразить степень своего согласия с ними, используя представленные варианты ответов (почти никогда, редко, часто, почти всегда).",
        "title": "Добро пожаловать 👋, Вы готовы?",
        "multiple": false,
        "required": true,
        "helpTextShow": false,
        "options": [{
          "label": "Давайте начнем",
          "value": "yeah"
        }],
        "model": ""
      },
      {
        "type": "multiplechoice",
        "id": "q1",
        "title": "Вопрос 1",
        "subtitle": "Меня редко раздражают мелочи.",
        "multiple": false,
        "required": true,
        "helpTextShow": false,
        "options": [{
            "label": "Почти всегда",
            "value": "always"
          },
          {
            "label": "Часто",
            "value": "often"
          },
          {
            "label": "Редко",
            "value": "rare"
          },
          {
            "label": "Почти никогда",
            "value": "never"
          }
        ],
        "model": ""
      },
      {
        "type": "multiplechoice",
        "id": "q2",
        "title": "Вопрос 2",
        "subtitle": "Я нервничаю, когда приходится кого-то ждать.",
        "multiple": false,
        "required": true,
        "helpTextShow": false,
        "options": [{
            "label": "Почти всегда",
            "value": "always"
          },
          {
            "label": "Часто",
            "value": "often"
          },
          {
            "label": "Редко",
            "value": "rare"
          },
          {
            "label": "Почти никогда",
            "value": "never"
          }
        ],
        "model": ""
      },
      {
        "type": "multiplechoice",
        "id": "q3",
        "title": "Вопрос 3",
        "subtitle": "Когда я попадаю в неловкое положение, то краснею.",
        "multiple": false,
        "required": true,
        "helpTextShow": false,
        "options": [{
            "label": "Почти всегда",
            "value": "always"
          },
          {
            "label": "Часто",
            "value": "often"
          },
          {
            "label": "Редко",
            "value": "rare"
          },
          {
            "label": "Почти никогда",
            "value": "never"
          }
        ],
        "model": ""
      },
      {
        "type": "multiplechoice",
        "id": "q4",
        "title": "Вопрос 4",
        "subtitle": "Когда я сержусь, то могу кого-нибудь обидеть.",
        "multiple": false,
        "required": true,
        "helpTextShow": false,
        "options": [{
            "label": "Почти всегда",
            "value": "always"
          },
          {
            "label": "Часто",
            "value": "often"
          },
          {
            "label": "Редко",
            "value": "rare"
          },
          {
            "label": "Почти никогда",
            "value": "never"
          }
        ],
        "model": ""
      },
      {
        "type": "multiplechoice",
        "id": "q5",
        "title": "Вопрос 5",
        "subtitle": "Не переношу критики, выхожу из себя.",
        "multiple": false,
        "required": true,
        "helpTextShow": false,
        "options": [{
            "label": "Почти всегда",
            "value": "always"
          },
          {
            "label": "Часто",
            "value": "often"
          },
          {
            "label": "Редко",
            "value": "rare"
          },
          {
            "label": "Почти никогда",
            "value": "never"
          }
        ],
        "model": ""
      },
      {
        "type": "multiplechoice",
        "id": "q6",
        "title": "Вопрос 6",
        "subtitle": "Если в транспорте меня толкнут, то отвечаю тем же или говорю что-нибудь грубое.",
        "multiple": false,
        "required": true,
        "helpTextShow": false,
        "options": [{
            "label": "Почти всегда",
            "value": "always"
          },
          {
            "label": "Часто",
            "value": "often"
          },
          {
            "label": "Редко",
            "value": "rare"
          },
          {
            "label": "Почти никогда",
            "value": "never"
          }
        ],
        "model": ""
      },
      {
        "type": "multiplechoice",
        "id": "q7",
        "title": "Вопрос 7",
        "subtitle": "Все свое свободное время чем-нибудь занят.",
        "multiple": false,
        "required": true,
        "helpTextShow": false,
        "options": [{
            "label": "Почти всегда",
            "value": "always"
          },
          {
            "label": "Часто",
            "value": "often"
          },
          {
            "label": "Редко",
            "value": "rare"
          },
          {
            "label": "Почти никогда",
            "value": "never"
          }
        ],
        "model": ""
      },
      {
        "type": "multiplechoice",
        "id": "q8",
        "title": "Вопрос 8",
        "subtitle": "На встречу всегда прихожу заранее или опаздываю.",
        "multiple": false,
        "required": true,
        "helpTextShow": false,
        "options": [{
            "label": "Почти всегда",
            "value": "always"
          },
          {
            "label": "Часто",
            "value": "often"
          },
          {
            "label": "Редко",
            "value": "rare"
          },
          {
            "label": "Почти никогда",
            "value": "never"
          }
        ],
        "model": ""
      },
      {
        "type": "multiplechoice",
        "id": "q9",
        "title": "Вопрос 9",
        "subtitle": "Не умею выслушивать, вставляю реплики.",
        "multiple": false,
        "required": true,
        "helpTextShow": false,
        "options": [{
            "label": "Почти всегда",
            "value": "always"
          },
          {
            "label": "Часто",
            "value": "often"
          },
          {
            "label": "Редко",
            "value": "rare"
          },
          {
            "label": "Почти никогда",
            "value": "never"
          }
        ],
        "model": ""
      },
      {
        "type": "multiplechoice",
        "id": "q10",
        "title": "Вопрос 10",
        "subtitle": "Страдаю отсутствием аппетита.",
        "multiple": false,
        "required": true,
        "helpTextShow": false,
        "options": [{
            "label": "Почти всегда",
            "value": "always"
          },
          {
            "label": "Часто",
            "value": "often"
          },
          {
            "label": "Редко",
            "value": "rare"
          },
          {
            "label": "Почти никогда",
            "value": "never"
          }
        ],
        "model": ""
      },
      {
        "type": "multiplechoice",
        "id": "q11",
        "title": "Вопрос 11",
        "subtitle": "Часто беспокоюсь без всякой причины.",
        "multiple": false,
        "required": true,
        "helpTextShow": false,
        "options": [{
            "label": "Почти всегда",
            "value": "always"
          },
          {
            "label": "Часто",
            "value": "often"
          },
          {
            "label": "Редко",
            "value": "rare"
          },
          {
            "label": "Почти никогда",
            "value": "never"
          }
        ],
        "model": ""
      },
      {
        "type": "multiplechoice",
        "id": "q12",
        "title": "Вопрос 12",
        "subtitle": "По утрам чувствую себя плохо.",
        "multiple": false,
        "required": true,
        "helpTextShow": false,
        "options": [{
            "label": "Почти всегда",
            "value": "always"
          },
          {
            "label": "Часто",
            "value": "often"
          },
          {
            "label": "Редко",
            "value": "rare"
          },
          {
            "label": "Почти никогда",
            "value": "never"
          }
        ],
        "model": ""
      },
      {
        "type": "multiplechoice",
        "id": "q13",
        "title": "Вопрос 13",
        "subtitle": "Чувствую себя уставшим, плохо сплю, не могу отключиться после продолжительного сна не чувствую себя нормально.",
        "multiple": false,
        "required": true,
        "helpTextShow": false,
        "options": [{
            "label": "Почти всегда",
            "value": "always"
          },
          {
            "label": "Часто",
            "value": "often"
          },
          {
            "label": "Редко",
            "value": "rare"
          },
          {
            "label": "Почти никогда",
            "value": "never"
          }
        ],
        "model": ""
      },
      {
        "type": "multiplechoice",
        "id": "q14",
        "title": "Вопрос 14",
        "subtitle": "Думаю, что сердце у меня не в порядке.",
        "multiple": false,
        "required": true,
        "helpTextShow": false,
        "options": [{
            "label": "Почти всегда",
            "value": "always"
          },
          {
            "label": "Часто",
            "value": "often"
          },
          {
            "label": "Редко",
            "value": "rare"
          },
          {
            "label": "Почти никогда",
            "value": "never"
          }
        ],
        "model": ""
      },
      {
        "type": "multiplechoice",
        "id": "q15",
        "title": "Вопрос 15",
        "subtitle": "У меня бывают боли в спине и шее.",
        "multiple": false,
        "required": true,
        "helpTextShow": false,
        "options": [{
            "label": "Почти всегда",
            "value": "always"
          },
          {
            "label": "Часто",
            "value": "often"
          },
          {
            "label": "Редко",
            "value": "rare"
          },
          {
            "label": "Почти никогда",
            "value": "never"
          }
        ],
        "model": ""
      },
      {
        "type": "multiplechoice",
        "id": "q16",
        "title": "Вопрос 16",
        "subtitle": "Когда сижу за столом, барабаню пальцами по столу и покачиваю ногой.",
        "multiple": false,
        "required": true,
        "helpTextShow": false,
        "options": [{
            "label": "Почти всегда",
            "value": "always"
          },
          {
            "label": "Часто",
            "value": "often"
          },
          {
            "label": "Редко",
            "value": "rare"
          },
          {
            "label": "Почти никогда",
            "value": "never"
          }
        ],
        "model": ""
      },
      {
        "type": "multiplechoice",
        "id": "q17",
        "title": "Вопрос 17",
        "subtitle": "Когда сижу за столом, барабаню пальцами по столу и покачиваю ногой.",
        "multiple": false,
        "required": true,
        "helpTextShow": false,
        "options": [{
            "label": "Почти всегда",
            "value": "always"
          },
          {
            "label": "Часто",
            "value": "often"
          },
          {
            "label": "Редко",
            "value": "rare"
          },
          {
            "label": "Почти никогда",
            "value": "never"
          }
        ],
        "model": ""
      },
      {
        "type": "multiplechoice",
        "id": "q18",
        "title": "Вопрос 18",
        "subtitle": "Мечтаю о признании, хочу, чтобы меня хвалили за то, что я делаю.",
        "multiple": false,
        "required": true,
        "helpTextShow": false,
        "options": [{
            "label": "Почти всегда",
            "value": "always"
          },
          {
            "label": "Часто",
            "value": "often"
          },
          {
            "label": "Редко",
            "value": "rare"
          },
          {
            "label": "Почти никогда",
            "value": "never"
          }
        ],
        "model": ""
      },
      {
        "type": "multiplechoice",
        "id": "q19",
        "title": "Вопрос 19",
        "subtitle": "Думаю, что я лучше многих.",
        "multiple": false,
        "required": true,
        "helpTextShow": false,
        "options": [{
            "label": "Почти всегда",
            "value": "always"
          },
          {
            "label": "Часто",
            "value": "often"
          },
          {
            "label": "Редко",
            "value": "rare"
          },
          {
            "label": "Почти никогда",
            "value": "never"
          }
        ],
        "model": ""
      },
      {
        "type": "multiplechoice",
        "id": "q20",
        "title": "Вопрос 20",
        "subtitle": "Я не соблюдаю диету.",
        "multiple": false,
        "required": true,
        "helpTextShow": false,
        "options": [{
            "label": "Почти всегда",
            "value": "always"
          },
          {
            "label": "Часто",
            "value": "often"
          },
          {
            "label": "Редко",
            "value": "rare"
          },
          {
            "label": "Почти никогда",
            "value": "never"
          }
        ],
        "model": ""
      }
    ]
  }